wxasync.py
wxasync-0.49.dist-info/LICENSE
wxasync-0.49.dist-info/METADATA
wxasync-0.49.dist-info/WHEEL
wxasync-0.49.dist-info/top_level.txt
wxasync-0.49.dist-info/zip-safe
wxasync-0.49.dist-info/RECORD
