Metadata-Version: 2.1
Name: wxasync
Version: 0.49
Summary: asyncio for wxpython
Home-page: http://github.com/sirk390/wxasync
Author: C.Bodt
Author-email: sirk390@gmail.com
License: MIT
Requires-Python: >=3.7
License-File: LICENSE
Requires-Dist: wxpython
